arato_client/__init__.py
arato_client/client.py
arato_client/exceptions.py
arato_client/models/__init__.py
arato_client/resources/__init__.py
arato_client/resources/base.py
arato_client/resources/datasets.py
arato_client/resources/evals.py
arato_client/resources/experiments.py
arato_client/resources/notebooks.py
arato_client/resources/runs.py
arato_client-1.0.10.dist-info/METADATA
arato_client-1.0.10.dist-info/WHEEL
arato_client-1.0.10.dist-info/top_level.txt
arato_client-1.0.10.dist-info/RECORD
