Metadata-Version: 2.4
Name: arato-client
Version: 1.0.10
Summary: The official Python Client for the Arato API for testing, experimenting, and evaluating LLM-based applications.
Author-email: Arato AI <support@arato.ai>
License: MIT License
Project-URL: Homepage, https://arato.ai
Project-URL: Documentation, https://help.arato.ai/en/
Classifier: Programming Language :: Python :: 3
Classifier: Operating System :: OS Independent
Classifier: License :: OSI Approved :: MIT License
Classifier: Intended Audience :: Developers
Classifier: Topic :: Software Development :: Libraries :: Python Modules
Requires-Python: >=3.8
Requires-Dist: httpx>=0.25.0
Requires-Dist: typing-extensions>=4.0.0
Provides-Extra: test
Requires-Dist: pytest>=7.4.0; extra == "test"
Requires-Dist: pytest-asyncio>=0.21.0; extra == "test"
Requires-Dist: pytest-cov>=4.1.0; extra == "test"
Requires-Dist: pytest-mock>=3.11.0; extra == "test"
